django_sendfile/__init__.py
django_sendfile/_version.py
django_sendfile/test_settings.py
django_sendfile/tests.py
django_sendfile/utils.py
django_sendfile/backends/__init__.py
django_sendfile/backends/development.py
django_sendfile/backends/mod_wsgi.py
django_sendfile/backends/nginx.py
django_sendfile/backends/simple.py
django_sendfile/backends/xsendfile.py
django_sendfile2-0.7.2.dist-info/licenses/LICENSE
django_sendfile2-0.7.2.dist-info/METADATA
django_sendfile2-0.7.2.dist-info/WHEEL
django_sendfile2-0.7.2.dist-info/top_level.txt
django_sendfile2-0.7.2.dist-info/zip-safe
django_sendfile2-0.7.2.dist-info/RECORD
